odoo/addons/hr_holidays_length_validation/README.rst
odoo/addons/hr_holidays_length_validation/__init__.py
odoo/addons/hr_holidays_length_validation/__manifest__.py
odoo/addons/hr_holidays_length_validation/i18n/fr.po
odoo/addons/hr_holidays_length_validation/i18n/hr_holidays_length_validation.pot
odoo/addons/hr_holidays_length_validation/i18n/it.po
odoo/addons/hr_holidays_length_validation/models/__init__.py
odoo/addons/hr_holidays_length_validation/models/hr_leave.py
odoo/addons/hr_holidays_length_validation/readme/CONTRIBUTORS.rst
odoo/addons/hr_holidays_length_validation/readme/DESCRIPTION.rst
odoo/addons/hr_holidays_length_validation/readme/USAGE.rst
odoo/addons/hr_holidays_length_validation/static/description/icon.png
odoo/addons/hr_holidays_length_validation/static/description/index.html
odoo/addons/hr_holidays_length_validation/tests/__init__.py
odoo/addons/hr_holidays_length_validation/tests/test_hr_holidays_length_validation.py
odoo/addons/hr_holidays_length_validation/views/hr_leave.xml
odoo12_addon_hr_holidays_length_validation-12.0.1.0.0.99.dev13.dist-info/METADATA
odoo12_addon_hr_holidays_length_validation-12.0.1.0.0.99.dev13.dist-info/WHEEL
odoo12_addon_hr_holidays_length_validation-12.0.1.0.0.99.dev13.dist-info/top_level.txt
odoo12_addon_hr_holidays_length_validation-12.0.1.0.0.99.dev13.dist-info/RECORD
